Metadata-Version: 1.0
Name: sparkworksws
Version: 0.0.14
Summary: A client library for the sparkworks websocket api
Home-page: https://api.sparkworks.net
Author: SparkWorks ITC
Author-email: info@sparkwokrs.net
License: UNKNOWN
Keywords: client,sparkworks,websocket
Platform: UNKNOWN
